emusica/__init__.py
emusica/argparse_prueba.py
emusica/descargar_audio.py
emusica/emusica.py
emusica/pruebas.py
emusica-0.0.7.dist-info/LICENCE
emusica-0.0.7.dist-info/METADATA
emusica-0.0.7.dist-info/WHEEL
emusica-0.0.7.dist-info/entry_points.txt
emusica-0.0.7.dist-info/top_level.txt
emusica-0.0.7.dist-info/RECORD
