Metadata-Version: 2.1
Name: emusica
Version: 0.0.7
Summary: Extrae música que está unida en un solo archivo y permite agregar sus metadatos
Home-page: https://github.com/MGCcoder/extractor-de-musica
Author: MGCcoder
Classifier: Programming Language :: Python :: 3
Classifier: License :: OSI Approved :: MIT License
Classifier: Operating System :: Unix
Classifier: Operating System :: Microsoft :: Windows
Classifier: Operating System :: MacOS
Requires-Python: >=3.10.6
License-File: LICENCE
